{
  "id": "",
  "name": "",
  "font_family": "iconfont",
  "css_prefix_text": "icon-",
  "description": "",
  "glyphs": [
    {
      "icon_id": "32471",
      "name": "cart",
      "font_class": "cart",
      "unicode": "e6af",
      "unicode_decimal": 59055
    },
    {
      "icon_id": "248956",
      "name": "gift",
      "font_class": "gift",
      "unicode": "e681",
      "unicode_decimal": 59009
    },
    {
      "icon_id": "880315",
      "name": "add",
      "font_class": "add",
      "unicode": "e6a8",
      "unicode_decimal": 59048
    },
    {
      "icon_id": "1174314",
      "name": "message",
      "font_class": "message",
      "unicode": "e668",
      "unicode_decimal": 58984
    },
    {
      "icon_id": "1488726",
      "name": "money",
      "font_class": "money",
      "unicode": "e669",
      "unicode_decimal": 58985
    },
    {
      "icon_id": "4765891",
      "name": "setting",
      "font_class": "setting",
      "unicode": "e78e",
      "unicode_decimal": 59278
    },
    {
      "icon_id": "4766954",
      "name": "star",
      "font_class": "star",
      "unicode": "e7df",
      "unicode_decimal": 59359
    },
    {
      "icon_id": "16619136",
      "name": "more",
      "font_class": "more",
      "unicode": "e6cb",
      "unicode_decimal": 59083
    },
    {
      "icon_id": "44063354",
      "name": "home",
      "font_class": "home",
      "unicode": "ea03",
      "unicode_decimal": 59907
    }
  ]
}
